django_basic_feedback/forms.py
django_basic_feedback/views.py
django_basic_feedback/models.py
django_basic_feedback/admin.py
django_basic_feedback/urls.py
django_basic_feedback/__init__.py
django_basic_feedback/templatetags/feedback_widget.py
django_basic_feedback/templatetags/__init__.py
django_basic_feedback/tests/test_urls.py
django_basic_feedback/tests/util.py
django_basic_feedback/tests/__init__.py
django_basic_feedback/static/feedback.js
django_basic_feedback/static/feedback.css
django_basic_feedback/templates/feedback/widget.html
django_basic_feedback_test_project/manage.py
django_basic_feedback_test_project/settings.py
django_basic_feedback_test_project/urls.py
django_basic_feedback_test_project/__init__.py
django_basic_feedback_test_project/runtests.py
django_basic_feedback-1.0.3.dist-info/DESCRIPTION.rst
django_basic_feedback-1.0.3.dist-info/RECORD
django_basic_feedback-1.0.3.dist-info/metadata.json
django_basic_feedback-1.0.3.dist-info/WHEEL
django_basic_feedback-1.0.3.dist-info/METADATA
django_basic_feedback-1.0.3.dist-info/top_level.txt
